{
  "updated_at": "2026-05-28T03:43:30.020823+00:00",
  "regions": {
    "10YIE-1001A00010": {
      "name": "Ireland",
      "total_mw": 2546,
      "renewable_mw": 1414,
      "wind_mw": 1414,
      "renewable_pct": 56,
      "mix": {
        "B04": 1052,
        "B05": 1,
        "B06": 3,
        "B08": 76,
        "B10": 0,
        "B11": 0,
        "B16": 0,
        "B20": 0,
        "B19": 1414
      }
    },
    "10Y1001A1001A83F": {
      "name": "Germany",
      "total_mw": 29388,
      "renewable_mw": 14417,
      "wind_mw": 7429,
      "renewable_pct": 49,
      "mix": {
        "B10": 755,
        "B01": 3846,
        "B02": 5904,
        "B03": 515,
        "B04": 4949,
        "B05": 2958,
        "B06": 379,
        "B09": 21,
        "B11": 1721,
        "B12": 51,
        "B15": 84,
        "B16": 59,
        "B17": 535,
        "B18": 1232,
        "B19": 6197,
        "B20": 182
      }
    },
    "10YFR-RTE------C": {
      "name": "France",
      "total_mw": 53583,
      "renewable_mw": 11340,
      "wind_mw": 3332,
      "renewable_pct": 21,
      "mix": {
        "B01": 469,
        "B04": 499,
        "B06": 35,
        "B10": 1102,
        "B11": 4659,
        "B12": 1381,
        "B14": 41613,
        "B16": 0,
        "B17": 396,
        "B18": 171,
        "B19": 3161,
        "B25": 96,
        "B05": 1
      }
    },
    "10Y1001A1001A65H": {
      "name": "Denmark",
      "total_mw": 2930,
      "renewable_mw": 2873,
      "wind_mw": 1985,
      "renewable_pct": 98,
      "mix": {
        "B01": 714,
        "B04": 52,
        "B06": 5,
        "B16": 17,
        "B17": 157,
        "B18": 1242,
        "B19": 743
      }
    },
    "10YNL----------L": {
      "name": "Netherlands",
      "total_mw": 9062,
      "renewable_mw": 1853,
      "wind_mw": 1418,
      "renewable_pct": 20,
      "mix": {
        "B01": 387,
        "B04": 5471,
        "B05": 1007,
        "B11": 0,
        "B14": 475,
        "B16": 0,
        "B17": 48,
        "B18": 1266,
        "B19": 151,
        "B20": 258
      }
    }
  }
}